ehiden/__init__.py
ehiden/ehiden_client.py
ehiden-0.1.1.dist-info/METADATA
ehiden-0.1.1.dist-info/WHEEL
ehiden-0.1.1.dist-info/RECORD
