Metadata-Version: 2.1
Name: ehiden
Version: 0.1.1
Summary: 
Author: HGS-Interman
Author-email: naofumi.higashikawauchi@interman.co.jp
Requires-Python: >=3.9,<4.0
Classifier: Programming Language :: Python :: 3
Classifier: Programming Language :: Python :: 3.9
Classifier: Programming Language :: Python :: 3.10
Classifier: Programming Language :: Python :: 3.11
Requires-Dist: lxml (>=4.9.3,<5.0.0)
Requires-Dist: pymupdf (>=1.23.3,<2.0.0)
Requires-Dist: requests (>=2.31.0,<3.0.0)
